BaseML/BaseClassification.py
BaseML/BaseCluster.py
BaseML/BaseDimentionReduction.py
BaseML/BaseRegression.py
BaseML/IMGLoader.py
BaseML/LICENSE
BaseML/__init__.py
BaseML/base.py
BaseML/version.py
BaseML/examples/__init__.py
BaseML/examples/boston_reg_demo.py
BaseML/examples/cart_demo.py
BaseML/examples/iris_cls_demo.py
BaseML/examples/iris_rdc_demo.py
BaseML/examples/kmeans_demo.py
BaseML/examples/knn_demo.py
baseml-2.0.0.dist-info/LICENSE
baseml-2.0.0.dist-info/METADATA
baseml-2.0.0.dist-info/WHEEL
baseml-2.0.0.dist-info/entry_points.txt
baseml-2.0.0.dist-info/top_level.txt
baseml-2.0.0.dist-info/zip-safe
baseml-2.0.0.dist-info/RECORD
